gograph/__init__.py
gograph/_modidx.py
gograph/algorithm.py
gograph/core.py
gograph/graph.py
gograph-0.0.11.dist-info/LICENSE
gograph-0.0.11.dist-info/METADATA
gograph-0.0.11.dist-info/WHEEL
gograph-0.0.11.dist-info/entry_points.txt
gograph-0.0.11.dist-info/top_level.txt
gograph-0.0.11.dist-info/RECORD
